{
    "name": "Greatsword",
    "displayName": "Greatsword",
    "description": "This immense two-handed sword is about 5 feet in length.",
    "shortDescription": "This immense two-handed sword is about 5 feet in length.",
    "equipable": true,
    "consumable": false,
    "type": "Weapon",
    "weight": 8,
    "price": 50,
    "source": "PZO1110",
    "attributes": {
        "slot": "Weapon",
        "size": "Medium",
        "damage": {
            "die": 2,
            "eyes": 6,
            "changes": {
                "die": 0,
                "eyes": 0,
                "damage": 0,
                "attackRoll": 0
            }
        },
        "criticalMultiplier": 2,
        "criticalRange": 1,
        "range": 0,
        "types": ["S"],
        "special": [],
        "proficiency": "Martial",
        "subtype": "Two-Handed Melee",
        "benefit": "",
        "condition": {
            "isMagical": false,
            "enhancementBonus": 0,
            "isComposite": false,
            "strengthRating": 0,
            "isMasterwork": false,
            "material": null
        }
    }
}
